HISTORY.rst
LICENSE
MANIFEST.in
README.rst
setup.py
todo.py
todo.py.egg-info/PKG-INFO
todo.py.egg-info/SOURCES.txt
todo.py.egg-info/dependency_links.txt
todo.py.egg-info/top_level.txt