Metadata-Version: 1.0
Name: todo.py
Version: 0.3-beta-3
Summary: Python version of Gina Trapani's popular bash script.
Home-page: https://github.com/sigmavirus24/Todo.txt-python
Author: graffatcolmingov
Author-email: graffatcolmingov@gmail.com
License: UNKNOWN
Platform: UNKNOWN
Classifier: Development Status :: 4 - Beta
Classifier: Environment :: Console
Classifier: License :: OSI Approved :: GNU General Public License v3 (GPLv3)
Classifier: Programming Language :: Python :: 2.6
Classifier: Programming Language :: Python :: 2.7
Classifier: Programming Language :: Python :: 3.2
Classifier: Programming Language :: Python :: Implementation :: CPython
Classifier: Programming Language :: Python :: Implementation :: IronPython
Classifier: Programming Language :: Python :: Implementation :: PyPy
